z3c.layer.ready2go-2.0-py3.9-nspkg.pth
z3c/layer/ready2go/README.txt
z3c/layer/ready2go/__init__.py
z3c/layer/ready2go/configure.zcml
z3c/layer/ready2go/ftesting.zcml
z3c/layer/ready2go/outputchecker.py
z3c/layer/ready2go/tests.py
z3c/layer/ready2go/z3c.layer.ready2go-configure.zcml
z3c.layer.ready2go-2.0.dist-info/LICENSE.txt
z3c.layer.ready2go-2.0.dist-info/METADATA
z3c.layer.ready2go-2.0.dist-info/WHEEL
z3c.layer.ready2go-2.0.dist-info/namespace_packages.txt
z3c.layer.ready2go-2.0.dist-info/top_level.txt
z3c.layer.ready2go-2.0.dist-info/RECORD
