Metadata-Version: 2.1
Name: z3c.layer.ready2go
Version: 2.0
Summary: A ready to go layer for Zope3
Home-page: https://github.com/zopefoundation/z3c.layer.ready2go
Author: Stephan Richter, Roger Ineichen and the Zope Community
Author-email: zope-dev@zope.dev
License: ZPL 2.1
Keywords: zope3 z3c ready 2 go layer
Classifier: Development Status :: 5 - Production/Stable
Classifier: Environment :: Web Environment
Classifier: Intended Audience :: Developers
Classifier: License :: OSI Approved :: Zope Public License
Classifier: Programming Language :: Python
Classifier: Programming Language :: Python :: 3
Classifier: Programming Language :: Python :: 3.7
Classifier: Programming Language :: Python :: 3.8
Classifier: Programming Language :: Python :: 3.9
Classifier: Programming Language :: Python :: 3.10
Classifier: Programming Language :: Python :: 3.11
Classifier: Programming Language :: Python :: Implementation :: CPython
Classifier: Programming Language :: Python :: Implementation :: PyPy
Classifier: Natural Language :: English
Classifier: Operating System :: OS Independent
Classifier: Topic :: Internet :: WWW/HTTP
Classifier: Framework :: Zope :: 3
Requires-Python: >=3.7
License-File: LICENSE.txt
Requires-Dist: setuptools
Requires-Dist: z3c.form
Requires-Dist: z3c.formui
Requires-Dist: z3c.layer.pagelet
Requires-Dist: zope.viewlet
Provides-Extra: test
Requires-Dist: WebTest ; extra == 'test'
Requires-Dist: lxml ; extra == 'test'
Requires-Dist: z3c.macro ; extra == 'test'
Requires-Dist: zope.app.wsgi ; extra == 'test'
Requires-Dist: zope.browserresource ; extra == 'test'
Requires-Dist: zope.principalregistry ; extra == 'test'
Requires-Dist: zope.publisher ; extra == 'test'
Requires-Dist: zope.security ; extra == 'test'
Requires-Dist: zope.securitypolicy ; extra == 'test'
Requires-Dist: zope.testing ; extra == 'test'
Requires-Dist: zope.testrunner ; extra == 'test'
Requires-Dist: z3c.form[test] ; extra == 'test'
Requires-Dist: zope.tal (>=4.0.0) ; extra == 'test'
